Metadata-Version: 2.1
Name: qadabra
Version: 0.3.0
Summary: Differential abundance workflow for microbiome data
Home-page: https://github.com/gibsramen/qadabra
Author: Gibraan Rahman
Author-email: grahman@eng.ucsd.edu
License: BSD-3-Clause
Classifier: Development Status :: 4 - Beta
Classifier: License :: OSI Approved :: BSD License
Classifier: Topic :: Software Development :: Libraries
Classifier: Topic :: Scientific/Engineering
Classifier: Topic :: Scientific/Engineering :: Bio-Informatics
Classifier: Programming Language :: Python :: 3
Classifier: Programming Language :: Python :: 3 :: Only
Classifier: Operating System :: Unix
Classifier: Operating System :: POSIX
Classifier: Operating System :: MacOS :: MacOS X
License-File: LICENSE
